Workbook

Sheet Tableau de bord
B2: Suivi d'avancement — formules dynamiques
B3: Ne pas saisir ici. Modifier le Statut et la Priorité dans l'onglet Backlog.
B5: Total features | C5: =COUNTA(Backlog!A2:A63) -> 62 | E5: P0 | F5: =COUNTIF(Backlog!E2:E63,"P0") -> 28
B6: À faire | C6: =COUNTIF(Backlog!G2:G63,"À faire") -> 62 | E6: P1 | F6: =COUNTIF(Backlog!E2:E63,"P1") -> 22
B7: En cours | C7: =COUNTIF(Backlog!G2:G63,"En cours") -> 0 | E7: P2 | F7: =COUNTIF(Backlog!E2:E63,"P2") -> 9
B8: En revue | C8: =COUNTIF(Backlog!G2:G63,"En revue") -> 0 | E8: P3 | F8: =COUNTIF(Backlog!E2:E63,"P3") -> 3
B9: Fait | C9: =COUNTIF(Backlog!G2:G63,"Fait") -> 0
B10: Bloqué | C10: =COUNTIF(Backlog!G2:G63,"Bloqué") -> 0 | E10: P0 encore ouverts | F10: =COUNTIFS(Backlog!E2:E63,"P0",Backlog!G2:G63,"<>Fait") -> 28
B11: Plus tard | C11: =COUNTIF(Backlog!G2:G63,"Plus tard") -> 0 | E11: P1 encore ouverts | F11: =COUNTIFS(Backlog!E2:E63,"P1",Backlog!G2:G63,"<>Fait") -> 22
B12: % fait | C12: =IF(C5=0,0,C9/C5) -> 0
B14: Par epic
B15: Epic | C15: Nb | D15: Fait | E15: Reste | F15: % fait
B16: Admin | C16: =COUNTIF(Backlog!B:B,B16) -> 3 | D16: =COUNTIFS(Backlog!B:B,B16,Backlog!G:G,"Fait") -> 0 | E16: =C16-D16 -> 3 | F16: =IF(C16=0,0,D16/C16) -> 0
B17: Audio | C17: =COUNTIF(Backlog!B:B,B17) -> 3 | D17: =COUNTIFS(Backlog!B:B,B17,Backlog!G:G,"Fait") -> 0 | E17: =C17-D17 -> 3 | F17: =IF(C17=0,0,D17/C17) -> 0
B18: Compte | C18: =COUNTIF(Backlog!B:B,B18) -> 3 | D18: =COUNTIFS(Backlog!B:B,B18,Backlog!G:G,"Fait") -> 0 | E18: =C18-D18 -> 3 | F18: =IF(C18=0,0,D18/C18) -> 0
B19: Confidentialité | C19: =COUNTIF(Backlog!B:B,B19) -> 1 | D19: =COUNTIFS(Backlog!B:B,B19,Backlog!G:G,"Fait") -> 0 | E19: =C19-D19 -> 1 | F19: =IF(C19=0,0,D19/C19) -> 0
B20: Espace parent | C20: =COUNTIF(Backlog!B:B,B20) -> 5 | D20: =COUNTIFS(Backlog!B:B,B20,Backlog!G:G,"Fait") -> 0 | E20: =C20-D20 -> 5 | F20: =IF(C20=0,0,D20/C20) -> 0
B21: Forêts | C21: =COUNTIF(Backlog!B:B,B21) -> 3 | D21: =COUNTIFS(Backlog!B:B,B21,Backlog!G:G,"Fait") -> 0 | E21: =C21-D21 -> 3 | F21: =IF(C21=0,0,D21/C21) -> 0
B22: Interactions | C22: =COUNTIF(Backlog!B:B,B22) -> 4 | D22: =COUNTIFS(Backlog!B:B,B22,Backlog!G:G,"Fait") -> 0 | E22: =C22-D22 -> 4 | F22: =IF(C22=0,0,D22/C22) -> 0
B23: Lecture enfant | C23: =COUNTIF(Backlog!B:B,B23) -> 4 | D23: =COUNTIFS(Backlog!B:B,B23,Backlog!G:G,"Fait") -> 0 | E23: =C23-D23 -> 4 | F23: =IF(C23=0,0,D23/C23) -> 0
B24: Leçons parentales | C24: =COUNTIF(Backlog!B:B,B24) -> 2 | D24: =COUNTIFS(Backlog!B:B,B24,Backlog!G:G,"Fait") -> 0 | E24: =C24-D24 -> 2 | F24: =IF(C24=0,0,D24/C24) -> 0
B25: Moteur narratif | C25: =COUNTIF(Backlog!B:B,B25) -> 6 | D25: =COUNTIFS(Backlog!B:B,B25,Backlog!G:G,"Fait") -> 0 | E25: =C25-D25 -> 6 | F25: =IF(C25=0,0,D25/C25) -> 0
B26: Production | C26: =COUNTIF(Backlog!B:B,B26) -> 4 | D26: =COUNTIFS(Backlog!B:B,B26,Backlog!G:G,"Fait") -> 0 | E26: =C26-D26 -> 4 | F26: =IF(C26=0,0,D26/C26) -> 0
B27: Profils | C27: =COUNTIF(Backlog!B:B,B27) -> 2 | D27: =COUNTIFS(Backlog!B:B,B27,Backlog!G:G,"Fait") -> 0 | E27: =C27-D27 -> 2 | F27: =IF(C27=0,0,D27/C27) -> 0
... B34: Éditorial | C34: =COUNTIF(Backlog!B:B,B34) -> 5 | D34: =COUNTIFS(Backlog!B:B,B34,Backlog!G:G,"Fait") -> 0 | E34: =C34-D34 -> 5 | F34: =IF(C34=0,0,D34/C34) -> 0
B37: Par phase
B38: Phase | C38: Nb | D38: Fait | E38: Reste
B39: Phase 2 | C39: =COUNTIF(Backlog!F:F,B39) -> 31 | D39: =COUNTIFS(Backlog!F:F,B39,Backlog!G:G,"Fait") -> 0 | E39: =C39-D39 -> 31
B40: Phase 1 | C40: =COUNTIF(Backlog!F:F,B40) -> 10 | D40: =COUNTIFS(Backlog!F:F,B40,Backlog!G:G,"Fait") -> 0 | E40: =C40-D40 -> 10
B41: Phase 0 | C41: =COUNTIF(Backlog!F:F,B41) -> 5 | D41: =COUNTIFS(Backlog!F:F,B41,Backlog!G:G,"Fait") -> 0 | E41: =C41-D41 -> 5
B42: Phase 4 | C42: =COUNTIF(Backlog!F:F,B42) -> 6 | D42: =COUNTIFS(Backlog!F:F,B42,Backlog!G:G,"Fait") -> 0 | E42: =C42-D42 -> 6
B43: Phase 3 | C43: =COUNTIF(Backlog!F:F,B43) -> 5 | D43: =COUNTIFS(Backlog!F:F,B43,Backlog!G:G,"Fait") -> 0 | E43: =C43-D43 -> 5
B44: Phase 5 | C44: =COUNTIF(Backlog!F:F,B44) -> 2 | D44: =COUNTIFS(Backlog!F:F,B44,Backlog!G:G,"Fait") -> 0 | E44: =C44-D44 -> 2
B45: Phase 6 | C45: =COUNTIF(Backlog!F:F,B45) -> 2 | D45: =COUNTIFS(Backlog!F:F,B45,Backlog!G:G,"Fait") -> 0 | E45: =C45-D45 -> 2
B46: Phase 7 | C46: =COUNTIF(Backlog!F:F,B46) -> 1 | D46: =COUNTIFS(Backlog!F:F,B46,Backlog!G:G,"Fait") -> 0 | E46: =C46-D46 -> 1

Sheet Lisez-moi
B2: Sentier — Backlog fonctionnel v2.0
B3: Identifiants stables pour branches Git, tickets et suivi d'avancement. Source : spécification fonctionnelle finale v2.0 (3 septembre 2026).
B5: Comment s'en servir
B6: 1. Une ligne = une feature développable, une branche Git suggérée.
B7: 2. L'ID ne change plus. On peut renommer le titre, pas l'identifiant.
B8: 3. Dans le dépôt : git checkout -b feat/F-ACC-001-compte-parent
B9: 4. Quand c'est commencé, passer Statut à « En cours » ; à « Fait » à la merge.
B10: 5. Le tableau de bord se met à jour tout seul (formules).
B12: Priorités
B13: P0 — Bloquant pour la première écoute réelle (profil + 1 arbre hors ligne).
B14: P1 — Dans le MVP livré aux premières familles.
B15: P2 — Juste après le MVP, pas dans la première découpe.
... B25: fix/<ID>-<slug> si correctif sur une feature déjà mergée

Sheet Backlog
A1: ID | B1: Epic | C1: Titre | D1: Description détaillée | E1: Priorité | F1: Phase | G1: Statut | H1: Dépendances | I1: Branche Git | J1: Assigné | K1: Notes
A2: F-ACC-001 | B2: Compte | C2: Création de compte parent | D2: Un adulte crée un compte (e-mail ou identité tierce). Confirmation qu'il a 18 ans et qu'il est responsable de l'enfant. CGU, confidentialité et consentement mineur présentés sans case précochée. E-mail vérifié avant génération ou téléchargement massif. Mot de passe robuste. 2FA recommandée, obligatoire plus tard sur les comptes payants. | E2: P0 | F2: Phase 2 | G2: À faire | H2: — | I2: feat/F-ACC-001-compte-parent
A3: F-ACC-002 | B3: Compte | C3: Connexion multi-appareils | D3: Le compte parent se synchronise entre appareils. La forêt locale reste propre à chaque appareil. L'historique léger est synchronisé pour éviter de rejouer immédiatement la même branche ailleurs, sauf réglage contraire. | E3: P1 | F3: Phase 2 | G3: À faire | H3: F-ACC-001 | I3: feat/F-ACC-002-multi-appareils
A4: F-ACC-003 | B4: Compte | C4: Consentements et portabilité | D4: Le parent consulte et retire : traitement du profil enfant, historique d'écoute, reconnaissance vocale future, journaux techniques, communications. Export lisible (leçons, validations, historique agrégé). Suppression de profil ou de compte avec effacement des audios locaux et des données perso côté serveur dans les délais légaux. | E4: P1 | F4: Phase 2 | G4: À faire | H4: F-ACC-001 | I4: feat/F-ACC-003-consentements
A5: F-SEC-001 | B5: Sécurité app | C5: Code parental | D5: Toutes les actions de configuration sont derrière un code 4 ou 6 chiffres distinct du mot de passe. Demandé : entrée espace parent depuis le mode enfant, validation/invalidation, modification des leçons/durée/stock, suppression de profil, export. Après 5 erreurs, délai croissant. Réinit via le compte authentifié, jamais depuis le mode enfant. Alternative biométrie ou geste complexe (SEC-001). | E5: P0 | F5: Phase 2 | G5: À faire | H5: F-ACC-001 | I5: feat/F-SEC-001-code-parental
A6: F-SEC-002 | B6: Sécurité app | C6: Cloisonnement mode enfant | D6: Le mode enfant n'expose ni achats, ni réglages, ni liens externes, ni données personnelles (SEC-002). Sortie uniquement par code parental. Pas de notifications commerciales pendant la session. | E6: P0 | F6: Phase 2 | G6: À faire | H6: F-SEC-001 | I6: feat/F-SEC-002-mode-enfant-clos
A7: F-PRF-001 | B7: Profils | C7: Profils enfants isolés | D7: Un compte peut avoir plusieurs profils. Chaque profil isole : leçons, forêt locale, historique, voix, niveau d'âge N1/N2/N3. Champs : prénom ou surnom, date de naissance ou tranche, pronom optionnel pour les accords, voix, mode jour/nuit par défaut, notes parentales jamais lues à l'enfant. | E7: P0 | F7: Phase 2 | G7: À faire | H7: F-ACC-001 | I7: feat/F-PRF-001-profils-enfants
A8: F-PRF-002 | B8: Profils | C8: Niveaux d'âge N1 N2 N3 | D8: Filtrage des arbres selon 3-4 / 4-5 / 5-6 ans. Si l'âge change, bascule après confirmation parentale. Les arbres trop simples ou trop complexes sont exclus. N1 : 2 choix, phrases courtes. N2 : cause-conséquence. N3 : jusqu'à 3 choix, transfert de leçon. | E8: P0 | F8: Phase 1 | G8: À faire | H8: F-PRF-001 | I8: feat/F-PRF-002-niveaux-age
A9: F-TAX-001 | B9: Référentiel | C9: Taxonomie domaine / sous-domaine / leçon | D9: Catalogue extensible à 3 niveaux. Une leçon peut apparaître dans plusieurs branches. Une branche a une leçon principale et des secondaires. Domaines V1 : santé, sécurité, émotions, différences quotidiennes, autonomie, famille, vie collective, monde vivant, temps, monde concret, sports, langage. | E9: P0 | F9: Phase 0 | G9: À faire | H9: — | I9: feat/F-TAX-001-taxonomie
A10: F-TAX-002 | B10: Référentiel | C10: Fiche leçon versionnée | D10: Chaque leçon : lesson_id, titre, âge, objectif observable, required_messages, forbidden_messages, misconceptions, success_behaviours, questions, sensibilité, version. Champs génération : framing, named_dangerous_actions, positive_scripts, banned_topics, family_model, emotion_lexicon, do_not_diagnose, compatible/incompatible lessons. | E10: P0 | F10: Phase 0 | G10: À faire | H10: F-TAX-001 | I10: feat/F-TAX-002-fiche-lecon
A11: F-TAX-003 | B11: Référentiel | C11: Sélection priorités exclusions parentales | D11: Le parent active un domaine, coche des leçons, ordonne un top de priorités, met « plus tard », exclut un thème. Score d'ordonnance : priorité + compatibilité + révision + intérêt − répétition − coût de transition − dépassement de durée. La priorité domine sans transition absurde. | E11: P0 | F11: Phase 2 | G11: À faire | H11: F-TAX-001;F-PRF-001 | I11: feat/F-TAX-003-priorites-parent
A12: F-TAX-004 | B12: Référentiel | C12: Versionnement et couverture | D12: Une modification des messages obligatoires/interdits crée une nouvelle version. Anciens arbres encore valides restent jouables mais ne sont plus renouvelés. Vue de couverture : leçons actives par domaine, jamais rencontrées, trop répétées. | E12: P2 | F12: Phase 4 | G12: À faire | H12: F-TAX-002 | I12: feat/F-TAX-004-versions-couverture
A13: F-NEU-001 | B13: Éditorial | C13: Vocabulaire neutre audio enfant | D13: L'audio enfant reste dans un français quotidien : maison, école, parc, papa, maman, frère, sœur, repas, animaux, règles simples. Interdit dans l'audio : religion, politique, guerre, crime, tuerie, discours de genre, deux papas / deux mamans. On n'explique pas ces sujets pour les rejeter : ils sont absents. Les listes d'exclusion restent en métadonnées (NEUT-001 à NEUT-005, RM-16, RM-17). | E13: P0 | F13: Phase 0 | G13: À faire | H13: F-TAX-002 | I13: feat/F-NEU-001-vocabulaire-neutre
... A63: F-V2-003 | B63: Version 2 | C63: Voice-to-voice spécialisé | D63: Entraînement vocal sur les mêmes tours de parole neutres. Dernière étape volontaire. N'est pas un argument de vente du MVP. | E63: P3 | F63: Phase 7 | G63: À faire | H63: F-V2-002 | I63: feat/F-V2-003-voice-to-voice

Sheet Sprint 0 — P0
B2: Première découpe conseillée — seulement les P0
B3: Objectif : un parent crée un profil, un arbre pilote validé se télécharge, l'enfant écoute hors ligne jusqu'à une fin, sans LLM.
B5: Ordre suggéré | C5: ID | D5: Titre | E5: Pourquoi maintenant
B6: 1 | C6: F-TAX-001 | D6: Taxonomie | E6: Sans leçons, rien à raconter.
B7: 2 | C7: F-TAX-002 | D7: Fiche leçon | E7: Contrat du générateur et des validateurs.
B8: 3 | C8: F-NEU-001 | D8: Vocabulaire neutre | E8: Règle éditoriale avant d'écrire la moindre scène.
B9: 4 | C9: F-NEU-002 | D9: Formulation positive | E9: Idem, sinon les arbres pilotes seront à jeter.
B10: 5 | C10: F-NAR-001 | D10: Modèle arbre | E10: Schéma JSON avant le moteur.
B11: 6 | C11: F-GEN-001 | D11: Chaîne génération | E11: Produire 1 à 6 arbres pilotes.
B12: 7 | C12: F-GEN-002 | D12: Simulateur | E12: Tous les chemins du parc pilote.
B13: 8 | C13: F-VAL-001 | D13: Validateurs | E13: Rien n'atteint l'enfant sans ça.
B14: 9 | C14: F-NEU-005 | D14: Validateur éditorial | E14: Neutralité + idées dangereuses.
B15: 10 | C15: F-AUD-001 | D15: Découpage audio | E15: Paquet jouable.
B16: 11 | C16: F-AUD-002 | D16: Durées réelles | E16: Le moteur en a besoin.
... B33: 28 | C33: F-PRI-001 | D33: Privacy de base | E33: Avant tout store.
